<annotation>
	<folder></folder>
	<filename>00000291_jpg.rf.685431cb1234b7250900ce8edd5bc708.jpg</filename>
	<path>00000291_jpg.rf.685431cb1234b7250900ce8edd5bc708.jpg</path>
	<source>
		<database>roboflow.ai</database>
	</source>
	<size>
		<width>640</width>
		<height>640</height>
		<depth>3</depth>
	</size>
	<segmented>0</segmented>
	<object>
		<name>plastic_bottle</name>
		<pose>Unspecified</pose>
		<truncated>0</truncated>
		<difficult>0</difficult>
		<occluded>0</occluded>
		<bndbox>
			<xmin>26</xmin>
			<xmax>154</xmax>
			<ymin>1</ymin>
			<ymax>641</ymax>
		</bndbox>
	</object>
	<object>
		<name>plastic_bottle</name>
		<pose>Unspecified</pose>
		<truncated>0</truncated>
		<difficult>0</difficult>
		<occluded>0</occluded>
		<bndbox>
			<xmin>171</xmin>
			<xmax>284</xmax>
			<ymin>196</ymin>
			<ymax>641</ymax>
		</bndbox>
	</object>
	<object>
		<name>plastic_bottle</name>
		<pose>Unspecified</pose>
		<truncated>0</truncated>
		<difficult>0</difficult>
		<occluded>0</occluded>
		<bndbox>
			<xmin>261</xmin>
			<xmax>382</xmax>
			<ymin>233</ymin>
			<ymax>641</ymax>
		</bndbox>
	</object>
	<object>
		<name>plastic_bottle</name>
		<pose>Unspecified</pose>
		<truncated>0</truncated>
		<difficult>0</difficult>
		<occluded>0</occluded>
		<bndbox>
			<xmin>355</xmin>
			<xmax>474</xmax>
			<ymin>106</ymin>
			<ymax>641</ymax>
		</bndbox>
	</object>
	<object>
		<name>plastic_bottle</name>
		<pose>Unspecified</pose>
		<truncated>0</truncated>
		<difficult>0</difficult>
		<occluded>0</occluded>
		<bndbox>
			<xmin>431</xmin>
			<xmax>563</xmax>
			<ymin>59</ymin>
			<ymax>641</ymax>
		</bndbox>
	</object>
	<object>
		<name>plastic_bottle</name>
		<pose>Unspecified</pose>
		<truncated>0</truncated>
		<difficult>0</difficult>
		<occluded>0</occluded>
		<bndbox>
			<xmin>545</xmin>
			<xmax>623</xmax>
			<ymin>381</ymin>
			<ymax>641</ymax>
		</bndbox>
	</object>
	<object>
		<name>plastic_bottle</name>
		<pose>Unspecified</pose>
		<truncated>0</truncated>
		<difficult>0</difficult>
		<occluded>0</occluded>
		<bndbox>
			<xmin>1</xmin>
			<xmax>76</xmax>
			<ymin>41</ymin>
			<ymax>641</ymax>
		</bndbox>
	</object>
</annotation>
