<annotation>
	<folder></folder>
	<filename>25_jpg.rf.408613bde6bacd35ae0f1308e0d191d6.jpg</filename>
	<path>25_jpg.rf.408613bde6bacd35ae0f1308e0d191d6.jpg</path>
	<source>
		<database>roboflow.ai</database>
	</source>
	<size>
		<width>640</width>
		<height>640</height>
		<depth>3</depth>
	</size>
	<segmented>0</segmented>
	<object>
		<name>plastic</name>
		<pose>Unspecified</pose>
		<truncated>0</truncated>
		<difficult>0</difficult>
		<occluded>0</occluded>
		<bndbox>
			<xmin>120</xmin>
			<xmax>531</xmax>
			<ymin>8</ymin>
			<ymax>641</ymax>
		</bndbox>
	</object>
</annotation>
