<annotation>
	<folder></folder>
	<filename>FUIYXMIHI_jpg.rf.94cc346655594a1dbd253c655ca78fe6.jpg</filename>
	<path>FUIYXMIHI_jpg.rf.94cc346655594a1dbd253c655ca78fe6.jpg</path>
	<source>
		<database>roboflow.ai</database>
	</source>
	<size>
		<width>640</width>
		<height>640</height>
		<depth>3</depth>
	</size>
	<segmented>0</segmented>
	<object>
		<name>plastic_bag</name>
		<pose>Unspecified</pose>
		<truncated>0</truncated>
		<difficult>0</difficult>
		<occluded>0</occluded>
		<bndbox>
			<xmin>235</xmin>
			<xmax>417</xmax>
			<ymin>199</ymin>
			<ymax>559</ymax>
		</bndbox>
	</object>
	<object>
		<name>plastic_bag</name>
		<pose>Unspecified</pose>
		<truncated>0</truncated>
		<difficult>0</difficult>
		<occluded>0</occluded>
		<bndbox>
			<xmin>134</xmin>
			<xmax>278</xmax>
			<ymin>145</ymin>
			<ymax>458</ymax>
		</bndbox>
	</object>
	<object>
		<name>plastic_bag</name>
		<pose>Unspecified</pose>
		<truncated>0</truncated>
		<difficult>0</difficult>
		<occluded>0</occluded>
		<bndbox>
			<xmin>59</xmin>
			<xmax>179</xmax>
			<ymin>108</ymin>
			<ymax>371</ymax>
		</bndbox>
	</object>
</annotation>
