<annotation>
	<folder></folder>
	<filename>metal101_jpg.rf.a9b9b4d06529fc995cb96c141c2d5918.jpg</filename>
	<path>metal101_jpg.rf.a9b9b4d06529fc995cb96c141c2d5918.jpg</path>
	<source>
		<database>roboflow.ai</database>
	</source>
	<size>
		<width>640</width>
		<height>640</height>
		<depth>3</depth>
	</size>
	<segmented>0</segmented>
	<object>
		<name>metel</name>
		<pose>Unspecified</pose>
		<truncated>0</truncated>
		<difficult>0</difficult>
		<occluded>0</occluded>
		<bndbox>
			<xmin>177</xmin>
			<xmax>611</xmax>
			<ymin>165</ymin>
			<ymax>597</ymax>
		</bndbox>
	</object>
</annotation>
