<annotation>
	<folder></folder>
	<filename>metal213_jpg.rf.26b746840ab9616c840621e43b81023d.jpg</filename>
	<path>metal213_jpg.rf.26b746840ab9616c840621e43b81023d.jpg</path>
	<source>
		<database>roboflow.ai</database>
	</source>
	<size>
		<width>640</width>
		<height>640</height>
		<depth>3</depth>
	</size>
	<segmented>0</segmented>
	<object>
		<name>metel</name>
		<pose>Unspecified</pose>
		<truncated>0</truncated>
		<difficult>0</difficult>
		<occluded>0</occluded>
		<bndbox>
			<xmin>121</xmin>
			<xmax>448</xmax>
			<ymin>173</ymin>
			<ymax>512</ymax>
		</bndbox>
	</object>
</annotation>
