<annotation>
	<folder></folder>
	<filename>metal202_jpg.rf.b0d15193019bcae7eddc330bbac41985.jpg</filename>
	<path>metal202_jpg.rf.b0d15193019bcae7eddc330bbac41985.jpg</path>
	<source>
		<database>roboflow.ai</database>
	</source>
	<size>
		<width>640</width>
		<height>640</height>
		<depth>3</depth>
	</size>
	<segmented>0</segmented>
	<object>
		<name>metel</name>
		<pose>Unspecified</pose>
		<truncated>0</truncated>
		<difficult>0</difficult>
		<occluded>0</occluded>
		<bndbox>
			<xmin>113</xmin>
			<xmax>519</xmax>
			<ymin>196</ymin>
			<ymax>586</ymax>
		</bndbox>
	</object>
</annotation>
