<annotation>
	<folder></folder>
	<filename>paper546_jpg.rf.e4f2503d245603dba1305176d55f7626.jpg</filename>
	<path>paper546_jpg.rf.e4f2503d245603dba1305176d55f7626.jpg</path>
	<source>
		<database>roboflow.ai</database>
	</source>
	<size>
		<width>640</width>
		<height>640</height>
		<depth>3</depth>
	</size>
	<segmented>0</segmented>
	<object>
		<name>paper</name>
		<pose>Unspecified</pose>
		<truncated>0</truncated>
		<difficult>0</difficult>
		<occluded>0</occluded>
		<bndbox>
			<xmin>31</xmin>
			<xmax>602</xmax>
			<ymin>1</ymin>
			<ymax>640</ymax>
		</bndbox>
		<polygon>
			<x1>410.416666</x1>
			<y1>0.925927</y1>
			<x2>264.583334</x2>
			<y2>0</y2>
			<x3>29.861111</x3>
			<y3>227.777778</y3>
			<x4>227.083334</x4>
			<y4>636.111112</y4>
			<x5>279.166666</x5>
			<y5>638.888888</y5>
			<x6>600.694445</x6>
			<y6>367.592593</y6>
			<x7>410.416666</x7>
			<y7>0.925927</y7>
		</polygon>
	</object>
</annotation>
