<annotation>
	<folder></folder>
	<filename>plastic140_jpg.rf.a77a045708c23b63ab5a90a5007dd58f.jpg</filename>
	<path>plastic140_jpg.rf.a77a045708c23b63ab5a90a5007dd58f.jpg</path>
	<source>
		<database>roboflow.ai</database>
	</source>
	<size>
		<width>640</width>
		<height>640</height>
		<depth>3</depth>
	</size>
	<segmented>0</segmented>
	<object>
		<name>plastic_bottle</name>
		<pose>Unspecified</pose>
		<truncated>0</truncated>
		<difficult>0</difficult>
		<occluded>0</occluded>
		<bndbox>
			<xmin>53</xmin>
			<xmax>616</xmax>
			<ymin>1</ymin>
			<ymax>515</ymax>
		</bndbox>
	</object>
</annotation>
