<annotation>
	<folder></folder>
	<filename>plastic28_jpg.rf.d39b7f6524349059cf79ad34e111cd02.jpg</filename>
	<path>plastic28_jpg.rf.d39b7f6524349059cf79ad34e111cd02.jpg</path>
	<source>
		<database>roboflow.ai</database>
	</source>
	<size>
		<width>640</width>
		<height>640</height>
		<depth>3</depth>
	</size>
	<segmented>0</segmented>
	<object>
		<name>plastic_bottle</name>
		<pose>Unspecified</pose>
		<truncated>0</truncated>
		<difficult>0</difficult>
		<occluded>0</occluded>
		<bndbox>
			<xmin>156</xmin>
			<xmax>641</xmax>
			<ymin>1</ymin>
			<ymax>641</ymax>
		</bndbox>
	</object>
</annotation>
